tests/__init__.py
tests/test_helper.py
tests/api/__init__.py
tests/api/test_api_base.py
tests/api/test_auth_api.py
tests/api/test_customer_api.py
tests/api/test_data_search_api.py
tests/api/test_mobile_api.py
tests/api/test_offline_api.py
tests/api/test_online_api.py
tests/api/test_payout_api.py
tests/api/test_recurring_api.py
yuansfer/__init__.py
yuansfer/api_helper.py
yuansfer/client.py
yuansfer/configuration.py
yuansfer/constant.py
yuansfer/decorators.py
yuansfer/exception.py
yuansfer/api/__init__.py
yuansfer/api/auth_api.py
yuansfer/api/base_api.py
yuansfer/api/customer_api.py
yuansfer/api/data_search_api.py
yuansfer/api/mobile_api.py
yuansfer/api/offline_api.py
yuansfer/api/online_api.py
yuansfer/api/payout_api.py
yuansfer/api/recurring_api.py
yuansfer/dto/__init__.py
yuansfer/dto/recurring/__init__.py
yuansfer/dto/recurring/paypal_billingcycle.py
yuansfer/dto/recurring/paypal_billingcycle_amount.py
yuansfer/dto/recurring/paypal_billingcycle_frequency.py
yuansfer/dto/recurring/paypal_billingcycle_pricingscheme.py
yuansfer/dto/recurring/paypal_billingcycle_tiers.py
yuansfer/dto/recurring/paypal_paymentpreferences.py
yuansfer/dto/recurring/paypal_paymentpreferences_setupfee.py
yuansfer/dto/recurring/paypal_productschema.py
yuansfer/dto/recurring/paypal_taxes.py
yuansfer/http/__init__.py
yuansfer/http/api_response.py
yuansfer/http/http_client.py
yuansfer/http/http_method_enum.py
yuansfer/http/http_request.py
yuansfer/http/http_response.py
yuansfer/http/requests_client.py
yuansfer-3.0.4.dist-info/LICENSE
yuansfer-3.0.4.dist-info/METADATA
yuansfer-3.0.4.dist-info/WHEEL
yuansfer-3.0.4.dist-info/top_level.txt
yuansfer-3.0.4.dist-info/RECORD
