Metadata-Version: 2.1
Name: yuansfer
Version: 3.0.4
Summary: Use Yuansfer SDK to manage and run business including payment, refund, customer
Home-page: https://docs.yuansfer.com/
Author: Shawn Zheng
Author-email: shawn@yuansfer.com
License: UNKNOWN
Platform: UNKNOWN
License-File: LICENSE
Requires-Dist: requests (<3.0,>=2.9.1)
Requires-Dist: python-dateutil (<3.0,>=2.5.3)
Requires-Dist: deprecation (>=2.0.6)
